vector_rag_gui/__init__.py
vector_rag_gui/cli.py
vector_rag_gui/completion.py
vector_rag_gui/logging_config.py
vector_rag_gui/api/__init__.py
vector_rag_gui/api/models.py
vector_rag_gui/api/routes.py
vector_rag_gui/api/server.py
vector_rag_gui/core/__init__.py
vector_rag_gui/core/agent.py
vector_rag_gui/core/query.py
vector_rag_gui/core/sdk_agent.py
vector_rag_gui/core/settings.py
vector_rag_gui/core/stores.py
vector_rag_gui/gui/__init__.py
vector_rag_gui/gui/main_window.py
vector_rag_gui/gui/worker.py
vector_rag_gui/icons/icon.png
vector_rag_gui/tools/__init__.py
vector_rag_gui/tools/aws_knowledge.py
vector_rag_gui/tools/file_tools.py
vector_rag_gui/tools/sdk_tools.py
vector_rag_gui/tools/todo_tools.py
vector_rag_gui/tools/vector_rag.py
vector_rag_gui/tools/web_fetch.py
vector_rag_gui/tools/web_search.py
vector_rag_gui-0.1.0.dist-info/METADATA
vector_rag_gui-0.1.0.dist-info/WHEEL
vector_rag_gui-0.1.0.dist-info/entry_points.txt
vector_rag_gui-0.1.0.dist-info/licenses/LICENSE
vector_rag_gui-0.1.0.dist-info/RECORD
