Metadata-Version: 2.4
Name: vector-rag-gui
Version: 0.1.0
Summary: Qt6 GUI for searching local vector RAG stores with markdown rendering
Project-URL: Homepage, https://github.com/dnvriend/vector-rag-gui
Project-URL: Repository, https://github.com/dnvriend/vector-rag-gui
Project-URL: Issues, https://github.com/dnvriend/vector-rag-gui/issues
Author-email: Dennis Vriend <dvriend@ilionx.com>
License: MIT
License-File: LICENSE
Keywords: cli,tool
Classifier: Development Status :: 4 - Beta
Classifier: Intended Audience :: Developers
Classifier: License :: OSI Approved :: MIT License
Classifier: Programming Language :: Python :: 3
Classifier: Programming Language :: Python :: 3.14
Requires-Python: >=3.14
Requires-Dist: anthropic>=0.40.0
Requires-Dist: anyio>=4.0.0
Requires-Dist: claude-agent-sdk>=0.1.12
Requires-Dist: click>=8.1.7
Requires-Dist: fastapi>=0.115.0
Requires-Dist: markdown>=3.5.0
Requires-Dist: pygments>=2.17.0
Requires-Dist: pyqt6-webengine>=6.6.0
Requires-Dist: pyqt6>=6.6.0
Requires-Dist: uvicorn>=0.32.0
Requires-Dist: vector-rag-tool>=0.1.0
